dnawave/__init__.py
dnawave/auth.py
dnawave/client.py
dnawave/exceptions.py
dnawave/utils.py
dnawave/models/__init__.py
dnawave/models/base.py
dnawave/models/dataset.py
dnawave/models/workflow.py
dnawave/models/workflow_run.py
dnawave-0.1.0.dist-info/LICENSE
dnawave-0.1.0.dist-info/METADATA
dnawave-0.1.0.dist-info/WHEEL
dnawave-0.1.0.dist-info/top_level.txt
dnawave-0.1.0.dist-info/RECORD
