Metadata-Version: 2.2
Name: dnawave
Version: 0.1.0
Summary: Official Python client for the DNAWave API
Author: DNAWave
Author-email: DNAWave <support@dnawave.io>
Requires-Python: >=3.7
License-File: LICENSE
Requires-Dist: requests>=2.25.0
Requires-Dist: urllib3>=1.26.0
Dynamic: author
Dynamic: requires-python
